pyusb_chain/UsbTreeView.exe
pyusb_chain/UsbTreeView.ini
pyusb_chain/UsbTreeView.txt
pyusb_chain/__init__.py
pyusb_chain/__main__.py
pyusb_chain/_version.py
pyusb_chain/usb_tree_view_tool.py
pyusb_chain/utility.py
pyusb_chain/devices/__init__.py
pyusb_chain/devices/altera_device.py
pyusb_chain/devices/audio_comport_device.py
pyusb_chain/devices/audio_device.py
pyusb_chain/devices/comport_device.py
pyusb_chain/devices/dsc_fsl_mc56_board.py
pyusb_chain/devices/usb_device.py
tests/__init__.py
tests/export_test.xml
tests/test_pyusb_chain.py
pyusb_chain-0.2.7.dist-info/LICENSE
pyusb_chain-0.2.7.dist-info/METADATA
pyusb_chain-0.2.7.dist-info/WHEEL
pyusb_chain-0.2.7.dist-info/entry_points.txt
pyusb_chain-0.2.7.dist-info/top_level.txt
pyusb_chain-0.2.7.dist-info/RECORD
